odoo8_addon_contract_commission-8.0.1.0.0.99.dev12-py3.8-nspkg.pth
odoo_addons/contract_commission/README.rst
odoo_addons/contract_commission/__init__.py
odoo_addons/contract_commission/__openerp__.py
odoo_addons/contract_commission/i18n/ca.po
odoo_addons/contract_commission/i18n/contract_commission.pot
odoo_addons/contract_commission/i18n/de.po
odoo_addons/contract_commission/i18n/el_GR.po
odoo_addons/contract_commission/i18n/es.po
odoo_addons/contract_commission/i18n/es_MX.po
odoo_addons/contract_commission/i18n/fi.po
odoo_addons/contract_commission/i18n/fr.po
odoo_addons/contract_commission/i18n/it.po
odoo_addons/contract_commission/i18n/pt_BR.po
odoo_addons/contract_commission/i18n/sk_SK.po
odoo_addons/contract_commission/i18n/sl.po
odoo_addons/contract_commission/i18n/zh_CN.po
odoo_addons/contract_commission/models/__init__.py
odoo_addons/contract_commission/models/account_analytic_account.py
odoo_addons/contract_commission/static/description/icon.png
odoo_addons/contract_commission/static/description/icon.svg
odoo_addons/contract_commission/tests/__init__.py
odoo_addons/contract_commission/tests/test_contract_commission.py
odoo8_addon_contract_commission-8.0.1.0.0.99.dev12.dist-info/METADATA
odoo8_addon_contract_commission-8.0.1.0.0.99.dev12.dist-info/WHEEL
odoo8_addon_contract_commission-8.0.1.0.0.99.dev12.dist-info/namespace_packages.txt
odoo8_addon_contract_commission-8.0.1.0.0.99.dev12.dist-info/top_level.txt
odoo8_addon_contract_commission-8.0.1.0.0.99.dev12.dist-info/RECORD
